full_adder.v
module full_adder (
    input  a,
    input  b,
    input  cin,
    output sum,
    output carry
);
    assign sum   = a ^ b ^ cin;
    assign carry = (a & b) | (b & cin) | (a & cin);
endmodule

tb_full_adder.v
module tb_full_adder;

    reg  a, b, cin;
    wire sum, carry;

    full_adder uut (
        .a(a),
        .b(b),
        .cin(cin),
        .sum(sum),
        .carry(carry)
    );

    initial begin
        $dumpfile("full_adder.vcd");
        $dumpvars(0, tb_full_adder);

        a = 0; b = 0; cin = 0; #10;
        a = 0; b = 0; cin = 1; #10;
        a = 0; b = 1; cin = 0; #10;
        a = 0; b = 1; cin = 1; #10;
        a = 1; b = 0; cin = 0; #10;
        a = 1; b = 0; cin = 1; #10;
        a = 1; b = 1; cin = 0; #10;
        a = 1; b = 1; cin = 1; #10;

        $finish;
    end

endmodule

full_adder.vcd
$date
	Tue Jan 06 18:37:03 2026
$end
$version
	Icarus Verilog
$end
$timescale
	1s
$end
$scope module tb_full_adder $end
$var wire 1 ! sum $end
$var wire 1 " carry $end
$var reg 1 # a $end
$var reg 1 $ b $end
$var reg 1 % cin $end
$scope module uut $end
$var wire 1 # a $end
$var wire 1 $ b $end
$var wire 1 " carry $end
$var wire 1 % cin $end
$var wire 1 ! sum $end
$upscope $end
$upscope $end
$enddefinitions $end
$comment Show the parameter values. $end
$dumpall
$end
#0
$dumpvars
0%
0$
0#
0"
0!
$end
#10
1!
1%
#20
0%
1$
#30
1"
0!
1%
#40
0"
1!
0%
0$
1#
#50
1"
0!
1%
#60
0%
1$
#70
1!
1%
