jkff.v
module jkff (
    input  j,
    input  k,
    input  clk,
    input  rst,
    output reg q
);

    always @(posedge clk or posedge rst) begin
        if (rst)
            q <= 1'b0;
        else begin
            case ({j, k})
                2'b00: q <= q;    // hold
                2'b01: q <= 1'b0; // reset
                2'b10: q <= 1'b1; // set
                2'b11: q <= ~q;   // toggle
            endcase
        end
    end

endmodule

tb_jkff.v
module tb_jkff;

    reg j, k, clk, rst;
    wire q;

    // Instantiate JK flip-flop
    jkff uut (
        .j(j),
        .k(k),
        .clk(clk),
        .rst(rst),
        .q(q)
    );

    // Clock generation: 10 ns period
    initial clk = 0;
    always #5 clk = ~clk;

    initial begin
        $dumpfile("jkff.vcd");
        $dumpvars(0, tb_jkff);

        // Initialize
        rst = 1;
        j = 0; k = 0;
        #12 rst = 0;

        // Hold (J=0, K=0)
        j = 0; k = 0; #20;

        // Reset (J=0, K=1)
        j = 0; k = 1; #20;

        // Set (J=1, K=0)
        j = 1; k = 0; #20;

        // Toggle (J=1, K=1)
        j = 1; k = 1; #40;

        $finish;
    end

endmodule

jkff.vcd
$date
	Wed Jan 07 21:38:07 2026
$end
$version
	Icarus Verilog
$end
$timescale
	1s
$end
$scope module tb_jkff $end
$var wire 1 ! q $end
$var reg 1 " clk $end
$var reg 1 # j $end
$var reg 1 $ k $end
$var reg 1 % rst $end
$scope module uut $end
$var wire 1 " clk $end
$var wire 1 # j $end
$var wire 1 $ k $end
$var wire 1 % rst $end
$var reg 1 ! q $end
$upscope $end
$upscope $end
$enddefinitions $end
$comment Show the parameter values. $end
$dumpall
$end
#0
$dumpvars
1%
0$
0#
0"
0!
$end
#5
1"
#10
0"
#12
0%
#15
1"
#20
0"
#25
1"
#30
0"
#32
1$
#35
1"
#40
0"
#45
1"
#50
0"
#52
0$
1#
#55
1!
1"
#60
0"
#65
1"
#70
0"
#72
1$
#75
0!
1"
#80
0"
#85
1!
1"
#90
0"
#95
0!
1"
#100
0"
#105
1!
1"
