mux_2x1.v
module mux_2x1 (
    input  a,
    input  b,
    input  sel,
    output y
);
    assign y = sel ? b : a;
endmodule

tb_mux_2x1.v
module tb_mux_2x1;

    reg  a, b, sel;
    wire y;

    // Instantiate 2x1 MUX
    mux_2x1 uut (
        .a(a),
        .b(b),
        .sel(sel),
        .y(y)
    );

    initial begin
        $dumpfile("mux_2x1.vcd");
        $dumpvars(0, tb_mux_2x1);

        // Test cases
        a = 0; b = 0; sel = 0; #10;
        a = 0; b = 1; sel = 0; #10;
        a = 1; b = 0; sel = 0; #10;
        a = 1; b = 1; sel = 0; #10;

        a = 0; b = 0; sel = 1; #10;
        a = 0; b = 1; sel = 1; #10;
        a = 1; b = 0; sel = 1; #10;
        a = 1; b = 1; sel = 1; #10;

        $finish;
    end

endmodule

mux_2x1.vcd
$date
	Wed Jan 07 21:44:31 2026
$end
$version
	Icarus Verilog
$end
$timescale
	1s
$end
$scope module tb_mux_2x1 $end
$var wire 1 ! y $end
$var reg 1 " a $end
$var reg 1 # b $end
$var reg 1 $ sel $end
$scope module uut $end
$var wire 1 " a $end
$var wire 1 # b $end
$var wire 1 $ sel $end
$var wire 1 ! y $end
$upscope $end
$upscope $end
$enddefinitions $end
$comment Show the parameter values. $end
$dumpall
$end
#0
$dumpvars
0$
0#
0"
0!
$end
#10
1#
#20
1!
0#
1"
#30
1#
#40
0!
1$
0#
0"
#50
1!
1#
#60
0!
0#
1"
#70
1!
1#
